easysnmp/interface.cpython-38-darwin.so
easysnmp/compat.py
easysnmp/variables.py
easysnmp/session.py
easysnmp/__init__.py
easysnmp/easy.py
easysnmp/utils.py
easysnmp/exceptions.py
easysnmp/helpers.py
easysnmp/.dylibs/libnetsnmp.40.dylib
easysnmp/.dylibs/libcrypto.1.1.dylib
easysnmp-0.2.6.dist-info/RECORD
easysnmp-0.2.6.dist-info/LICENSE
easysnmp-0.2.6.dist-info/WHEEL
easysnmp-0.2.6.dist-info/top_level.txt
easysnmp-0.2.6.dist-info/METADATA
